ReFreSH/CSharp/Linq.py
ReFreSH/CSharp/__init__.py
ReFreSH/ConsoleColor.py
ReFreSH/DependencyInjection.py
ReFreSH/MobileSuit/Core/ColorSetting.py
ReFreSH/MobileSuit/Core/ISuitCommandServer.py
ReFreSH/MobileSuit/Core/ISuitMiddleware.py
ReFreSH/MobileSuit/Core/Middlewares/AppShellMiddleware.py
ReFreSH/MobileSuit/Core/Middlewares/FinalizeMiddleware.py
ReFreSH/MobileSuit/Core/Middlewares/HostShellMiddleware.py
ReFreSH/MobileSuit/Core/Middlewares/PromptMiddleware.py
ReFreSH/MobileSuit/Core/Middlewares/UserInputMiddleware.py
ReFreSH/MobileSuit/Core/Middlewares/__init__.py
ReFreSH/MobileSuit/Core/Services/AppInfo.py
ReFreSH/MobileSuit/Core/Services/HistoryService.py
ReFreSH/MobileSuit/Core/Services/IOHub.py
ReFreSH/MobileSuit/Core/Services/ParsingService.py
ReFreSH/MobileSuit/Core/Services/PromptFormatter.py
ReFreSH/MobileSuit/Core/Services/SuitAppShell.py
ReFreSH/MobileSuit/Core/Services/SuitCommandServer.py
ReFreSH/MobileSuit/Core/Services/SuitExceptionHandler.py
ReFreSH/MobileSuit/Core/Services/SuitHostShell.py
ReFreSH/MobileSuit/Core/Services/TaskService.py
ReFreSH/MobileSuit/Core/Services/__init__.py
ReFreSH/MobileSuit/Core/SuitBuildUtils.py
ReFreSH/MobileSuit/Core/SuitContext.py
ReFreSH/MobileSuit/Core/SuitMethodParameterInfo.py
ReFreSH/MobileSuit/Core/SuitMethodShell.py
ReFreSH/MobileSuit/Core/SuitObjectShell.py
ReFreSH/MobileSuit/Core/SuitParser.py
ReFreSH/MobileSuit/Core/SuitShell.py
ReFreSH/MobileSuit/Core/TestSuitMethodShell2.py
ReFreSH/MobileSuit/Core/__init__.py
ReFreSH/MobileSuit/Decorators/DecoratorNames.py
ReFreSH/MobileSuit/Decorators/DecoratorUtils.py
ReFreSH/MobileSuit/Decorators/SuitArgParser.py
ReFreSH/MobileSuit/Decorators/__init__.py
ReFreSH/MobileSuit/IIOHub.py
ReFreSH/MobileSuit/OutputType.py
ReFreSH/MobileSuit/PrintUnit.py
ReFreSH/MobileSuit/RequestStatus.py
ReFreSH/MobileSuit/Resources/BuildInCommandInformations.en.yaml
ReFreSH/MobileSuit/Resources/BuildInCommandInformations.zh.yaml
ReFreSH/MobileSuit/Resources/Lang.en.yaml
pymobilesuit-0.1.2.dist-info/METADATA
pymobilesuit-0.1.2.dist-info/WHEEL
pymobilesuit-0.1.2.dist-info/RECORD
