Metadata-Version: 2.1
Name: PyMobileSuit
Version: 0.1.2
Summary: An easy way to build python-CLI App quickly, MobileSuit provides an easy way to build Console App quickly. For python.
Home-page: https://github.com/HIT-ReFreSH/PyMobileSuit
License: MIT
Keywords: commandline,cli,framework,HIT-ReFreSH
Author: Ferdinand Sukhoi
Author-email: ferdinandsukhoi@outlook.com
Requires-Python: >=3.9
Classifier: License :: OSI Approved :: MIT License
Classifier: Programming Language :: Python :: 3
Classifier: Programming Language :: Python :: 3.9
Classifier: Programming Language :: Python :: 3.10
Classifier: Programming Language :: Python :: 3.11
Classifier: Programming Language :: Python :: 3.12
Classifier: Programming Language :: Python :: 3.13
Requires-Dist: colour (>=0.1.5,<0.2.0)
Requires-Dist: pyasn1 (>=0.6.1,<0.7.0)
Requires-Dist: pyyaml (>=6.0.1,<6.1.0)
Project-URL: Repository, https://github.com/HIT-ReFreSH/PyMobileSuit
